edx_dl/__init__.py
edx_dl/_version.py
edx_dl/common.py
edx_dl/edx_dl.py
edx_dl/parsing.py
edx_dl/utils.py
edx_dl-0.1.13.dist-info/AUTHORS.md
edx_dl-0.1.13.dist-info/LICENSE
edx_dl-0.1.13.dist-info/METADATA
edx_dl-0.1.13.dist-info/WHEEL
edx_dl-0.1.13.dist-info/entry_points.txt
edx_dl-0.1.13.dist-info/top_level.txt
edx_dl-0.1.13.dist-info/RECORD
