Metadata-Version: 2.1
Name: edx-dl
Version: 0.1.13
Summary: Simple tool to download video and lecture materials from edx.org.
Home-page: https://github.com/coursera-dl/edx-dl
Maintainer: Ismaël Mejía, Rogério Theodoro de Brito, Yuri Bochkarev
Maintainer-email: iemejia@gmail.com, rbrito@ime.usp.br, baltazar.bz@gmail.com
License: LGPL
Keywords: edx-dl,edX,download,education,MOOCs,video
Platform: any
Classifier: Development Status :: 4 - Beta
Classifier: Environment :: Console
Classifier: Intended Audience :: End Users/Desktop
Classifier: License :: OSI Approved :: GNU Lesser General Public License v3 or later (LGPLv3+)
Classifier: Operating System :: OS Independent
Classifier: Programming Language :: Python :: 2
Classifier: Programming Language :: Python :: 2.7
Classifier: Programming Language :: Python :: 3
Classifier: Programming Language :: Python :: 3.5
Classifier: Programming Language :: Python :: 3.6
Classifier: Programming Language :: Python :: 3.7
Classifier: Programming Language :: Python :: 3.8
Classifier: Programming Language :: Python :: Implementation :: CPython
Classifier: Programming Language :: Python :: Implementation :: PyPy
Classifier: Programming Language :: Python
Classifier: Topic :: Education
Requires-Dist: beautifulsoup4 (>=4.6.0)
Requires-Dist: html5lib (>=1.0.1)
Requires-Dist: six (>=1.11.0)
Requires-Dist: youtube-dl (>=2018.06.18)
Requires-Dist: requests (>=2.18.4)
Provides-Extra: dev
Requires-Dist: pytest (>=2.5) ; extra == 'dev'
Requires-Dist: pytest-cov ; extra == 'dev'
Requires-Dist: pandoc ; extra == 'dev'
